rosbag_compare/__init__.py
rosbag_compare/__main__.py
rosbag_compare/comparator.py
rosbag_compare-0.1.1.dist-info/LICENSE
rosbag_compare-0.1.1.dist-info/METADATA
rosbag_compare-0.1.1.dist-info/WHEEL
rosbag_compare-0.1.1.dist-info/entry_points.txt
rosbag_compare-0.1.1.dist-info/top_level.txt
rosbag_compare-0.1.1.dist-info/RECORD
