Metadata-Version: 2.1
Name: rosbag-compare
Version: 0.1.1
Summary: Compare topics between rosbags
Home-page: https://github.com/IamPhytan/rosbag-compare
Author: damienlarocque
Author-email: phicoltan@gmail.com
License: MIT
Platform: UNKNOWN
Classifier: License :: OSI Approved :: MIT License
Classifier: Programming Language :: Python :: 3
Classifier: Programming Language :: Python :: 3.9
License-File: LICENSE
Requires-Dist: rosbags
Requires-Dist: tqdm
Requires-Dist: matplotlib
